svnm/__init__.py
svnm/__main__.py
svnm/basemodels.py
svnm/cifar10.py
svnm/config.py
svnm/face_recognition.py
svnm/facedetection.py
svnm/facerecognition.py
svnm/genderdetection.py
svnm/handwrittendigitrecognition.py
svnm/layers.py
svnm/models.py
svnm/preprocessing.py
svnm/projects.py
svnm/utils.py
svnm/welcome.py
svnm-1.4.2.dist-info/METADATA
svnm-1.4.2.dist-info/WHEEL
svnm-1.4.2.dist-info/top_level.txt
svnm-1.4.2.dist-info/RECORD
