Metadata-Version: 2.2
Name: svnm
Version: 1.4.2
Summary: A package to make the usage of DeepLearning models easier
Home-page: https://github.com/svnmurali-2004/svnm
Author: svn.murali
Author-email: svnmurali1@gmail.com
Classifier: Programming Language :: Python :: 3
Classifier: License :: OSI Approved :: MIT License
Classifier: Operating System :: OS Independent
Requires-Python: >=3.6
Requires-Dist: huggingface_hub
Requires-Dist: matplotlib
Requires-Dist: numpy
Requires-Dist: pandas
Requires-Dist: pyfiglet
Requires-Dist: setuptools
Requires-Dist: tensorflow-cpu
Requires-Dist: termcolor
Requires-Dist: ultralytics
Requires-Dist: opencv-python
Requires-Dist: keras_facenet
Requires-Dist: deepface
Dynamic: author
Dynamic: author-email
Dynamic: classifier
Dynamic: description
Dynamic: description-content-type
Dynamic: home-page
Dynamic: requires-dist
Dynamic: requires-python
Dynamic: summary
